agentmail_toolkit/__init__.py
agentmail_toolkit/functions.py
agentmail_toolkit/langchain.py
agentmail_toolkit/livekit.py
agentmail_toolkit/openai.py
agentmail_toolkit/py.typed
agentmail_toolkit/schemas.py
agentmail_toolkit/toolkit.py
agentmail_toolkit/tools.py
agentmail_toolkit-0.1.35.dist-info/METADATA
agentmail_toolkit-0.1.35.dist-info/WHEEL
agentmail_toolkit-0.1.35.dist-info/RECORD
