Metadata-Version: 2.4
Name: agentmail-toolkit
Version: 0.1.35
Summary: AgentMail Toolkit
Requires-Python: >=3.11
Requires-Dist: agentmail>=0.1.10
Requires-Dist: filetype>=1.2.0
Requires-Dist: langchain>=1.1.0
Requires-Dist: livekit-agents>=1.3.5
Requires-Dist: openai-agents>=0.6.1
Requires-Dist: pydantic>=2.12.5
Requires-Dist: pymupdf>=1.26.6
Requires-Dist: python-docx>=1.2.0
